pycdp_old/__init__.py
pycdp_old/asyncio.py
pycdp_old/base.py
pycdp_old/browser.py
pycdp_old/cdp/__init__.py
pycdp_old/cdp/accessibility.py
pycdp_old/cdp/animation.py
pycdp_old/cdp/audits.py
pycdp_old/cdp/background_service.py
pycdp_old/cdp/browser.py
pycdp_old/cdp/cache_storage.py
pycdp_old/cdp/cast.py
pycdp_old/cdp/console.py
pycdp_old/cdp/css.py
pycdp_old/cdp/database.py
pycdp_old/cdp/debugger.py
pycdp_old/cdp/device_orientation.py
pycdp_old/cdp/dom.py
pycdp_old/cdp/dom_debugger.py
pycdp_old/cdp/dom_snapshot.py
pycdp_old/cdp/dom_storage.py
pycdp_old/cdp/emulation.py
pycdp_old/cdp/event_breakpoints.py
pycdp_old/cdp/fetch.py
pycdp_old/cdp/headless_experimental.py
pycdp_old/cdp/heap_profiler.py
pycdp_old/cdp/indexed_db.py
pycdp_old/cdp/input_.py
pycdp_old/cdp/inspector.py
pycdp_old/cdp/io.py
pycdp_old/cdp/layer_tree.py
pycdp_old/cdp/log.py
pycdp_old/cdp/media.py
pycdp_old/cdp/memory.py
pycdp_old/cdp/network.py
pycdp_old/cdp/overlay.py
pycdp_old/cdp/page.py
pycdp_old/cdp/performance.py
pycdp_old/cdp/performance_timeline.py
pycdp_old/cdp/profiler.py
pycdp_old/cdp/py.typed
pycdp_old/cdp/runtime.py
pycdp_old/cdp/schema.py
pycdp_old/cdp/security.py
pycdp_old/cdp/service_worker.py
pycdp_old/cdp/storage.py
pycdp_old/cdp/system_info.py
pycdp_old/cdp/target.py
pycdp_old/cdp/tethering.py
pycdp_old/cdp/tracing.py
pycdp_old/cdp/util.py
pycdp_old/cdp/web_audio.py
pycdp_old/cdp/web_authn.py
pycdp_old/exceptions.py
pycdp_old/gen/README.md
pycdp_old/gen/__init__.py
pycdp_old/gen/browser_protocol.json
pycdp_old/gen/generate.py
pycdp_old/gen/js_protocol.json
pycdp_old/gen/test_generate.py
pycdp_old/twisted.py
pycdp_old/utils.py
python_cdp_old-1.3.0.dist-info/METADATA
python_cdp_old-1.3.0.dist-info/WHEEL
python_cdp_old-1.3.0.dist-info/entry_points.txt
python_cdp_old-1.3.0.dist-info/licenses/LICENSE
python_cdp_old-1.3.0.dist-info/RECORD
