Metadata-Version: 2.4
Name: python-cdp-old
Version: 1.3.0
Summary: Old Python type wrappers for Chrome DevTools Protocol (CDP)
License: MIT
License-File: LICENSE
Author: Mark E. Haase
Author-email: mehaase@gmail.com
Requires-Python: >=3.8,<4.0
Classifier: Development Status :: 3 - Alpha
Classifier: Intended Audience :: Developers
Classifier: License :: OSI Approved :: MIT License
Classifier: Programming Language :: Python :: 3
Classifier: Programming Language :: Python :: 3.8
Classifier: Programming Language :: Python :: 3.9
Classifier: Programming Language :: Python :: 3.10
Classifier: Programming Language :: Python :: 3.11
Classifier: Programming Language :: Python :: 3.12
Classifier: Programming Language :: Python :: 3.13
Classifier: Programming Language :: Python :: 3.14
Classifier: Programming Language :: Python :: 3 :: Only
Classifier: Topic :: Internet
Requires-Dist: aiohttp (>=3.8.3,<4.0.0)
Requires-Dist: deprecated (==1.2.9)
Requires-Dist: inflection (==0.4.0)
Project-URL: Homepage, https://github.com/HMaker/python-cdp
